[{"shirtNumber":1,"firstName":"Hugo","lastName":"Lloris","originId":17965,"slugName":"hugo-lloris","mainPosition":"Goalkeeper","dateOfBirth":"Dec 26, 1986","age":31,"height":"1,88 m","foot":"left","joined":"Aug 31, 2012","contractUntil":"30.06.2022","marketValue":"30,00 Mill. €"},{"shirtNumber":13,"firstName":"Michel","lastName":"Vorm","originId":26276,"slugName":"michel-vorm","mainPosition":"Goalkeeper","dateOfBirth":"Oct 20, 1983","age":35,"height":"1,83 m","foot":"right","joined":"Jul 23, 2014","contractUntil":"30.06.2019","marketValue":"2,50 Mill. €"},{"shirtNumber":22,"firstName":"Paulo","lastName":"Gazzaniga","originId":195488,"slugName":"paulo-gazzaniga","mainPosition":"Goalkeeper","dateOfBirth":"Jan 2, 1992","age":26,"height":"1,95 m","foot":"right","joined":"Aug 23, 2017","contractUntil":"30.06.2022","marketValue":"1,00 Mill. €"},{"shirtNumber":4,"firstName":"Toby","lastName":"Alderweireld","originId":42710,"slugName":"toby-alderweireld","mainPosition":"Centre-Back","dateOfBirth":"Mar 2, 1989","age":29,"height":"1,86 m","foot":"right","joined":"Jul 8, 2015","contractUntil":"30.06.2019","marketValue":"40,00 Mill. €"},{"shirtNumber":6,"firstName":"Davinson","lastName":"Sánchez","originId":341429,"slugName":"davinson-sanchez","mainPosition":"Centre-Back","dateOfBirth":"Jun 12, 1996","age":22,"height":"1,87 m","foot":"right","joined":"Aug 23, 2017","contractUntil":"30.06.2024","marketValue":"40,00 Mill. €"},{"shirtNumber":5,"firstName":"Jan","lastName":"Vertonghen","originId":43250,"slugName":"jan-vertonghen","mainPosition":"Centre-Back","dateOfBirth":"Apr 24, 1987","age":31,"height":"1,89 m","foot":"left","joined":"Jul 12, 2012","contractUntil":"30.06.2019","marketValue":"32,00 Mill. €"},{"shirtNumber":21,"firstName":"Juan","lastName":"Foyth","originId":480763,"slugName":"juan-foyth","mainPosition":"Centre-Back","dateOfBirth":"Jan 12, 1998","age":20,"height":"1,87 m","foot":"right","joined":"Aug 30, 2017","contractUntil":"30.06.2022","marketValue":"5,00 Mill. €"},{"shirtNumber":3,"firstName":"Danny","lastName":"Rose","originId":50174,"slugName":"danny-rose","mainPosition":"Left-Back","dateOfBirth":"Jul 2, 1990","age":28,"height":"1,73 m","foot":"left","joined":"Jul 25, 2007","contractUntil":"30.06.2021","marketValue":"30,00 Mill. €"},{"shirtNumber":33,"firstName":"Ben","lastName":"Davies","originId":192765,"slugName":"ben-davies","mainPosition":"Left-Back","dateOfBirth":"Apr 24, 1993","age":25,"height":"1,81 m","foot":"left","joined":"Jul 23, 2014","contractUntil":"30.06.2021","marketValue":"25,00 Mill. €"},{"shirtNumber":2,"firstName":"Kieran","lastName":"Trippier","originId":95810,"slugName":"kieran-trippier","mainPosition":"Right-Back","dateOfBirth":"Sep 19, 1990","age":28,"height":"1,74 m","foot":"right","joined":"Jul 1, 2015","contractUntil":"30.06.2022","marketValue":"35,00 Mill. €"},{"shirtNumber":24,"firstName":"Serge","lastName":"Aurier","originId":127032,"slugName":"serge-aurier","mainPosition":"Right-Back","dateOfBirth":"Dec 24, 1992","age":25,"height":"1,76 m","foot":"right","joined":"Aug 31, 2017","contractUntil":"30.06.2022","marketValue":"20,00 Mill. €"},{"shirtNumber":16,"firstName":"Kyle","lastName":"Walker-Peters","originId":341051,"slugName":"kyle-walker-peters","mainPosition":"Right-Back","dateOfBirth":"Apr 13, 1997","age":21,"height":"1,73 m","foot":"right","joined":"Jul 1, 2017","contractUntil":"30.06.2021","marketValue":"3,00 Mill. €"},{"shirtNumber":15,"firstName":"Eric","lastName":"Dier","originId":175722,"slugName":"eric-dier","mainPosition":"Defensive Midfield","dateOfBirth":"Jan 15, 1994","age":24,"height":"1,89 m","foot":"right","joined":"Jul 31, 2014","contractUntil":"30.06.2021","marketValue":"40,00 Mill. €"},{"shirtNumber":12,"firstName":"Victor","lastName":"Wanyama","originId":77760,"slugName":"victor-wanyama","mainPosition":"Defensive Midfield","dateOfBirth":"Jun 25, 1991","age":27,"height":"1,84 m","foot":"right","joined":"Jul 1, 2016","contractUntil":"30.06.2021","marketValue":"30,00 Mill. €"},{"shirtNumber":17,"firstName":"Moussa","lastName":"Sissoko","originId":46001,"slugName":"moussa-sissoko","mainPosition":"Central Midfield","dateOfBirth":"Aug 16, 1989","age":29,"height":"1,87 m","foot":"right","joined":"Aug 31, 2016","contractUntil":"30.06.2021","marketValue":"18,00 Mill. €"},{"shirtNumber":19,"firstName":"Mousa","lastName":"Dembélé","originId":19368,"slugName":"mousa-dembele","mainPosition":"Central Midfield","dateOfBirth":"Jul 16, 1987","age":31,"height":"1,85 m","foot":"left","joined":"Aug 29, 2012","contractUntil":"30.06.2019","marketValue":"18,00 Mill. €"},{"shirtNumber":8,"firstName":"Harry","lastName":"Winks","originId":249126,"slugName":"harry-winks","mainPosition":"Central Midfield","dateOfBirth":"Feb 2, 1996","age":22,"height":"1,78 m","foot":"right","joined":"Jul 1, 2016","contractUntil":"30.06.2023","marketValue":"15,00 Mill. €"},{"shirtNumber":20,"firstName":"Dele","lastName":"Alli","originId":207929,"slugName":"dele-alli","mainPosition":"Attacking Midfield","dateOfBirth":"Apr 11, 1996","age":22,"height":"1,88 m","foot":"right","joined":"Feb 2, 2015","contractUntil":"30.06.2024","marketValue":"100,00 Mill. €"},{"shirtNumber":23,"firstName":"Christian","lastName":"Eriksen","originId":69633,"slugName":"christian-eriksen","mainPosition":"Attacking Midfield","dateOfBirth":"Feb 14, 1992","age":26,"height":"1,82 m","foot":"both","joined":"Aug 30, 2013","contractUntil":"30.06.2020","marketValue":"80,00 Mill. €"},{"shirtNumber":7,"firstName":"Heung-min","lastName":"Son","originId":91845,"slugName":"heung-min-son","mainPosition":"Left Winger","dateOfBirth":"Jul 8, 1992","age":26,"height":"1,84 m","foot":"both","joined":"Aug 28, 2015","contractUntil":"30.06.2023","marketValue":"50,00 Mill. €"},{"shirtNumber":14,"firstName":"Georges-Kevin","lastName":"N'Koudou","originId":215679,"slugName":"georges-kevin-nkoudou","mainPosition":"Left Winger","dateOfBirth":"Feb 13, 1995","age":23,"height":"1,74 m","foot":"right","joined":"Aug 31, 2016","contractUntil":"30.06.2021","marketValue":"7,00 Mill. €"},{"shirtNumber":27,"firstName":"Lucas","lastName":"Moura","originId":77100,"slugName":"lucas-moura","mainPosition":"Right Winger","dateOfBirth":"Aug 13, 1992","age":26,"height":"1,72 m","foot":"right","joined":"Jan 31, 2018","contractUntil":"30.06.2023","marketValue":"32,00 Mill. €"},{"shirtNumber":11,"firstName":"Érik","lastName":"Lamela","originId":111630,"slugName":"erik-lamela","mainPosition":"Right Winger","dateOfBirth":"Mar 4, 1992","age":26,"height":"1,84 m","foot":"left","joined":"Aug 30, 2013","contractUntil":"30.06.2022","marketValue":"20,00 Mill. €"},{"shirtNumber":10,"firstName":"Harry","lastName":"Kane","originId":132098,"slugName":"harry-kane","mainPosition":"Centre-Forward","dateOfBirth":"Jul 28, 1993","age":25,"height":"1,88 m","foot":"right","joined":"Jan 1, 2011","contractUntil":"30.06.2024","marketValue":"150,00 Mill. €"},{"shirtNumber":9,"firstName":"Vincent","lastName":"Janssen","originId":207015,"slugName":"vincent-janssen","mainPosition":"Centre-Forward","dateOfBirth":"Jun 15, 1994","age":24,"height":"1,83 m","foot":"left","joined":"Jul 12, 2016","contractUntil":"30.06.2020","marketValue":"9,00 Mill. €"},{"shirtNumber":18,"firstName":"Fernando","lastName":"Llorente","originId":35564,"slugName":"fernando-llorente","mainPosition":"Centre-Forward","dateOfBirth":"Feb 26, 1985","age":33,"height":"1,93 m","foot":"right","joined":"Aug 31, 2017","contractUntil":"30.06.2019","marketValue":"5,00 Mill. €"}]